pylint_string_spaces_checkers-0.2.4.dist-info/DESCRIPTION.rst
pylint_string_spaces_checkers-0.2.4.dist-info/METADATA
pylint_string_spaces_checkers-0.2.4.dist-info/RECORD
pylint_string_spaces_checkers-0.2.4.dist-info/WHEEL
pylint_string_spaces_checkers-0.2.4.dist-info/metadata.json
pylint_string_spaces_checkers-0.2.4.dist-info/top_level.txt
string_spaces_checkers/__init__.py
