Metadata-Version: 2.0
Name: pylint-string-spaces-checkers
Version: 0.2.4
Summary: Additional string spaces checkers for Pylint
Home-page: UNKNOWN
Author: ZhangBohan
Author-email: me@bohanzhang.com
License: UNKNOWN
Download-URL: https://github.com/ZhangBohan/pylint-string-spaces-checkers.git
Platform: UNKNOWN
Classifier: Intended Audience :: Developers
Classifier: Environment :: Console
Classifier: Programming Language :: Python
Classifier: Topic :: Software Development
Requires-Dist: pylint
